mpay/__init__.py
mpay-0.0.1.dist-info/METADATA
mpay-0.0.1.dist-info/WHEEL
mpay-0.0.1.dist-info/licenses/LICENSE
mpay-0.0.1.dist-info/RECORD
